pclone/__init__.py
pclone-0.0.1.dist-info/METADATA
pclone-0.0.1.dist-info/WHEEL
pclone-0.0.1.dist-info/entry_points.txt
pclone-0.0.1.dist-info/top_level.txt
pclone-0.0.1.dist-info/RECORD
