Metadata-Version: 2.1
Name: pclone
Version: 0.0.1
Summary: Command line utility for clone files
Home-page: UNKNOWN
Author: UNKNOWN
Author-email: UNKNOWN
License: UNKNOWN
Platform: UNKNOWN
